<?xml version="1.0" encoding="UTF-8"?>
<blueprint xmlns="http://www.osgi.org/xmlns/blueprint/v1.0.0" xmlns:xsi="http://www.w3.org/2001/XMLSchema-instance" xmlns:tx="http://aries.apache.org/xmlns/transactions/v1.1.0"
  xmlns:jpa="http://aries.apache.org/xmlns/jpa/v2.0.0" xsi:schemaLocation="http://www.osgi.org/xmlns/blueprint/v1.0.0 https://osgi.org/xmlns/blueprint/v1.0.0/blueprint.xsd">

  <jpa:enable />

  <bean id="alignmentDAOImpl" class="org.renci.hearsay.dao.jpa.AlignmentDAOImpl">
    <tx:transaction method="*" value="Required" />
  </bean>
  <bean id="canonicalAlleleDAOImpl" class="org.renci.hearsay.dao.jpa.CanonicalAlleleDAOImpl">
    <tx:transaction method="*" value="Required" />
  </bean>
  <bean id="chromosomeDAOImpl" class="org.renci.hearsay.dao.jpa.ChromosomeDAOImpl">
    <tx:transaction method="*" value="Required" />
  </bean>
  <bean id="diagnosticResultDAOImpl" class="org.renci.hearsay.dao.jpa.DiagnosticResultDAOImpl">
    <tx:transaction method="*" value="Required" />
  </bean>
  <bean id="featureDAOImpl" class="org.renci.hearsay.dao.jpa.FeatureDAOImpl">
    <tx:transaction method="*" value="Required" />
  </bean>
  <bean id="geneDAOImpl" class="org.renci.hearsay.dao.jpa.GeneDAOImpl">
    <tx:transaction method="*" value="Required" />
  </bean>
  <bean id="geneSymbolDAOImpl" class="org.renci.hearsay.dao.jpa.GeneSymbolDAOImpl">
    <tx:transaction method="*" value="Required" />
  </bean>
  <bean id="genomeReferenceDAOImpl" class="org.renci.hearsay.dao.jpa.GenomeReferenceDAOImpl">
    <tx:transaction method="*" value="Required" />
  </bean>
  <bean id="identifierDAOImpl" class="org.renci.hearsay.dao.jpa.IdentifierDAOImpl">
    <tx:transaction method="*" value="Required" />
  </bean>
  <bean id="intronOffsetDAOImpl" class="org.renci.hearsay.dao.jpa.IntronOffsetDAOImpl">
    <tx:transaction method="*" value="Required" />
  </bean>
  <bean id="locationDAOImpl" class="org.renci.hearsay.dao.jpa.LocationDAOImpl">
    <tx:transaction method="*" value="Required" />
  </bean>
  <bean id="molecularConsequenceDAOImpl" class="org.renci.hearsay.dao.jpa.MolecularConsequenceDAOImpl">
    <tx:transaction method="*" value="Required" />
  </bean>
  <bean id="participantDAOImpl" class="org.renci.hearsay.dao.jpa.ParticipantDAOImpl">
    <tx:transaction method="*" value="Required" />
  </bean>
  <bean id="populationFrequencyDAOImpl" class="org.renci.hearsay.dao.jpa.PopulationFrequencyDAOImpl">
    <tx:transaction method="*" value="Required" />
  </bean>
  <bean id="referenceCoordinateDAOImpl" class="org.renci.hearsay.dao.jpa.ReferenceCoordinateDAOImpl">
    <tx:transaction method="*" value="Required" />
  </bean>
  <bean id="referenceSequenceDAOImpl" class="org.renci.hearsay.dao.jpa.ReferenceSequenceDAOImpl">
    <tx:transaction method="*" value="Required" />
  </bean>
  <bean id="regionDAOImpl" class="org.renci.hearsay.dao.jpa.RegionDAOImpl">
    <tx:transaction method="*" value="Required" />
  </bean>
  <bean id="roleDAOImpl" class="org.renci.hearsay.dao.jpa.RoleDAOImpl">
    <tx:transaction method="*" value="Required" />
  </bean>
  <bean id="simpleAlleleDAOImpl" class="org.renci.hearsay.dao.jpa.SimpleAlleleDAOImpl">
    <tx:transaction method="*" value="Required" />
  </bean>
  <bean id="userDAOImpl" class="org.renci.hearsay.dao.jpa.UserDAOImpl">
    <tx:transaction method="*" value="Required" />
  </bean>

  <service ref="alignmentDAOImpl" interface="org.renci.hearsay.dao.AlignmentDAO" />
  <service ref="canonicalAlleleDAOImpl" interface="org.renci.hearsay.dao.CanonicalAlleleDAO" />
  <service ref="chromosomeDAOImpl" interface="org.renci.hearsay.dao.ChromosomeDAO" />
  <service ref="diagnosticResultDAOImpl" interface="org.renci.hearsay.dao.DiagnosticResultDAO" />
  <service ref="featureDAOImpl" interface="org.renci.hearsay.dao.FeatureDAO" />
  <service ref="geneDAOImpl" interface="org.renci.hearsay.dao.GeneDAO" />
  <service ref="geneSymbolDAOImpl" interface="org.renci.hearsay.dao.GeneSymbolDAO" />
  <service ref="genomeReferenceDAOImpl" interface="org.renci.hearsay.dao.GenomeReferenceDAO" />
  <service ref="identifierDAOImpl" interface="org.renci.hearsay.dao.IdentifierDAO" />
  <service ref="intronOffsetDAOImpl" interface="org.renci.hearsay.dao.IntronOffsetDAO" />
  <service ref="locationDAOImpl" interface="org.renci.hearsay.dao.LocationDAO" />
  <service ref="molecularConsequenceDAOImpl" interface="org.renci.hearsay.dao.MolecularConsequenceDAO" />
  <service ref="participantDAOImpl" interface="org.renci.hearsay.dao.ParticipantDAO" />
  <service ref="populationFrequencyDAOImpl" interface="org.renci.hearsay.dao.PopulationFrequencyDAO" />
  <service ref="referenceCoordinateDAOImpl" interface="org.renci.hearsay.dao.ReferenceCoordinateDAO" />
  <service ref="referenceSequenceDAOImpl" interface="org.renci.hearsay.dao.ReferenceSequenceDAO" />
  <service ref="regionDAOImpl" interface="org.renci.hearsay.dao.RegionDAO" />
  <service ref="roleDAOImpl" interface="org.renci.hearsay.dao.RoleDAO" />
  <service ref="simpleAlleleDAOImpl" interface="org.renci.hearsay.dao.SimpleAlleleDAO" />
  <service ref="userDAOImpl" interface="org.renci.hearsay.dao.UserDAO" />

  <bean id="hearsayDAOBeanService" class="org.renci.hearsay.dao.HearsayDAOBean">
    <property name="alignmentDAO" ref="alignmentDAOImpl" />
    <property name="chromosomeDAO" ref="chromosomeDAOImpl" />
    <property name="canonicalAlleleDAO" ref="canonicalAlleleDAOImpl" />
    <property name="featureDAO" ref="featureDAOImpl" />
    <property name="geneDAO" ref="geneDAOImpl" />
    <property name="geneSymbolDAO" ref="geneSymbolDAOImpl" />
    <property name="identifierDAO" ref="identifierDAOImpl" />
    <property name="intronOffsetDAO" ref="intronOffsetDAOImpl" />
    <property name="locationDAO" ref="locationDAOImpl" />
    <property name="molecularConsequenceDAO" ref="molecularConsequenceDAOImpl" />
    <property name="populationFrequencyDAO" ref="populationFrequencyDAOImpl" />
    <property name="referenceCoordinateDAO" ref="referenceCoordinateDAOImpl" />
    <property name="regionDAO" ref="regionDAOImpl" />
    <property name="genomeReferenceDAO" ref="genomeReferenceDAOImpl" />
    <property name="referenceSequenceDAO" ref="referenceSequenceDAOImpl" />
    <property name="simpleAlleleDAO" ref="simpleAlleleDAOImpl" />
  </bean>
  <service ref="hearsayDAOBeanService" interface="org.renci.hearsay.dao.HearsayDAOBeanService" />

</blueprint>


